package_name/__init__.py
package_name/module1_name/__init__.py
package_name/module1_name/file1_name.py
package_name/module1_name/file2_name.py
package_name/module2_name/__init__.py
package_name/module2_name/file1_name.py
package_name/module2_name/file2_name.py
PedroDornela-0.0.1.dist-info/METADATA
PedroDornela-0.0.1.dist-info/WHEEL
PedroDornela-0.0.1.dist-info/top_level.txt
PedroDornela-0.0.1.dist-info/RECORD
