Metadata-Version: 2.1
Name: PedroDornela
Version: 0.0.1
Summary: My short description
Home-page: https://github.com/pedrodornela/package-template
Author: Pedro
Author-email: pedro.henriquedgoncalves@gmail.com
License: UNKNOWN
Platform: UNKNOWN
Requires-Python: >=3.7
Requires-Dist: matplotlib
Requires-Dist: numpy
Requires-Dist: scikit-image (>=0.16.1)
